pulse/__init__.py
pulse/client.py
pulse/core/__init__.py
pulse/core/api_error.py
pulse/core/client_wrapper.py
pulse/core/datetime_utils.py
pulse/core/file.py
pulse/core/force_multipart.py
pulse/core/http_client.py
pulse/core/http_response.py
pulse/core/http_sse/__init__.py
pulse/core/http_sse/_api.py
pulse/core/http_sse/_decoders.py
pulse/core/http_sse/_exceptions.py
pulse/core/http_sse/_models.py
pulse/core/jsonable_encoder.py
pulse/core/pydantic_utilities.py
pulse/core/query_encoder.py
pulse/core/remove_none_from_dict.py
pulse/core/request_options.py
pulse/core/serialization.py
pulse/core/unchecked_base_model.py
pulse/environment.py
pulse/errors/__init__.py
pulse/errors/bad_request_error.py
pulse/errors/forbidden_error.py
pulse/errors/internal_server_error.py
pulse/errors/not_found_error.py
pulse/errors/too_many_requests_error.py
pulse/errors/unauthorized_error.py
pulse/jobs/__init__.py
pulse/jobs/client.py
pulse/jobs/raw_client.py
pulse/py.typed
pulse/raw_client.py
pulse/types/__init__.py
pulse/types/extract_async_request_experimental_schema.py
pulse/types/extract_async_request_schema.py
pulse/types/extract_async_request_storage.py
pulse/types/extract_async_request_structured_output.py
pulse/types/extract_async_response.py
pulse/types/extract_async_submission_response_status.py
pulse/types/extract_input.py
pulse/types/extract_input_experimental_schema.py
pulse/types/extract_input_schema.py
pulse/types/extract_input_storage.py
pulse/types/extract_input_structured_output.py
pulse/types/extract_options.py
pulse/types/extract_options_experimental_schema.py
pulse/types/extract_options_schema.py
pulse/types/extract_options_storage.py
pulse/types/extract_options_structured_output.py
pulse/types/extract_request_experimental_schema.py
pulse/types/extract_request_schema.py
pulse/types/extract_request_storage.py
pulse/types/extract_request_structured_output.py
pulse/types/extract_response.py
pulse/types/extract_source.py
pulse/types/job_cancellation_response.py
pulse_python_sdk-0.0.62.dist-info/METADATA
pulse_python_sdk-0.0.62.dist-info/WHEEL
pulse_python_sdk-0.0.62.dist-info/RECORD
